do_audit/__init__.py
do_audit/api.py
do_audit/command_line.py
do_audit/utils.py
do_audit/test/conftest.py
do_audit/test/test_command_line.py
do_audit/test/test_utils.py
do_audit/test/cassettes/TestAccountSubcommand.yaml
do_audit/test/cassettes/TestDomainsSubcommand.yaml
do_audit/test/cassettes/TestDropletsSubcommand.yaml
do_audit-0.1.1.data/scripts/do-audit
do_audit-0.1.1.dist-info/DESCRIPTION.rst
do_audit-0.1.1.dist-info/METADATA
do_audit-0.1.1.dist-info/RECORD
do_audit-0.1.1.dist-info/WHEEL
do_audit-0.1.1.dist-info/metadata.json
do_audit-0.1.1.dist-info/top_level.txt
