Metadata-Version: 2.0
Name: do-audit
Version: 0.1.1
Summary: Audit your Digital Ocean account and make sure you know what's up
Home-page: https://github.com/omni-digital/do-audit
Author: Omni Digital
Author-email: developers@omni-digital.co.uk
License: MIT License
Download-URL: https://github.com/omni-digital/do-audit/releases/latest
Keywords: digital ocean audit do cli
Platform: UNKNOWN
Classifier: Development Status :: 4 - Beta
Classifier: Environment :: Console
Classifier: Intended Audience :: End Users/Desktop
Classifier: License :: OSI Approved :: MIT License
Classifier: Operating System :: OS Independent
Classifier: Programming Language :: Python
Classifier: Programming Language :: Python :: 2
Classifier: Programming Language :: Python :: 2.7
Classifier: Programming Language :: Python :: 3
Classifier: Programming Language :: Python :: 3.4
Classifier: Programming Language :: Python :: 3.5
Classifier: Programming Language :: Python :: 3.6
Classifier: Topic :: Utilities
Requires-Dist: click (>=6.7)
Requires-Dist: dnspython (>=1.15.0)
Requires-Dist: python-dateutil (>=2.6.0)
Requires-Dist: python-digitalocean (>=1.11)
Requires-Dist: requests (>=2.18.1)
Requires-Dist: six (>=1.10.0)
Requires-Dist: tablib (>=0.11.5)
Provides-Extra: testing
Requires-Dist: pytest; extra == 'testing'
Requires-Dist: pytest-mock; extra == 'testing'
